waldur_site_agent_croit_s3/__init__.py
waldur_site_agent_croit_s3/backend.py
waldur_site_agent_croit_s3/client.py
waldur_site_agent_croit_s3/exceptions.py
waldur_site_agent_croit_s3-0.8.2.dist-info/METADATA
waldur_site_agent_croit_s3-0.8.2.dist-info/WHEEL
waldur_site_agent_croit_s3-0.8.2.dist-info/entry_points.txt
waldur_site_agent_croit_s3-0.8.2.dist-info/RECORD
