Metadata-Version: 2.4
Name: waldur-site-agent-croit-s3
Version: 0.8.2
Summary: Croit S3 storage plugin for Waldur Site Agent
Author-email: OpenNode Team <info@opennodecloud.com>
Requires-Python: <4,>=3.9
Requires-Dist: boto3>=1.40.71
Requires-Dist: requests>=2.25.0
Requires-Dist: urllib3>=1.26.0
Requires-Dist: waldur-site-agent>=0.7.0
